Metadata-Version: 2.1
Name: hiword
Version: 0.5.1
Summary: Hi, word!
Home-page: https://github.com/jadbin/hiword
Author: jadbin
Author-email: jadbin.com@hotmail.com
License: Apache 2
Platform: UNKNOWN
Classifier: License :: OSI Approved :: Apache Software License
Classifier: Intended Audience :: Developers
Classifier: Programming Language :: Python
Classifier: Programming Language :: Python :: 3
Classifier: Topic :: Software Development :: Libraries :: Python Modules
Requires-Python: >=3.5
License-File: LICENSE
